yta_audio_editor/__init__.py
yta_audio_editor-0.0.6.dist-info/LICENSE
yta_audio_editor-0.0.6.dist-info/METADATA
yta_audio_editor-0.0.6.dist-info/WHEEL
yta_audio_editor-0.0.6.dist-info/RECORD
